{
    "Arapahoe Basin": {
        "today": {
            "temps": {
                "min_temp": 11.19,
                "max_temp": 15.33,
                "avg_temp": 13.06
            },
            "vis": {
                "min_vis": 14400.0,
                "max_vis": 22300.0,
                "avg_vis": 16866.67
            },
            "snow": {
                "total_snow": 0.0
            },
            "wind": {
                "avg_wind": 28.69,
                "max_gusts": 51.12,
                "avg_gusts": 42
            }
        },
        "three_day": {
            "temps": {
                "min_temp": 11.19,
                "max_temp": 30.27,
                "avg_temp": 17.82
            },
            "vis": {
                "min_vis": 14400.0,
                "max_vis": 63600.0,
                "avg_vis": 33648.15
            },
            "snow": {
                "total_snow": 0.0
            },
            "wind": {
                "avg_wind": 14.89,
                "max_gusts": 51.12,
                "avg_gusts": 23
            }
        },
        "seven_day": {
            "temps": {
                "min_temp": 6.42,
                "max_temp": 35.85,
                "avg_temp": 17.56
            },
            "vis": {
                "min_vis": 200.0,
                "max_vis": 63600.0,
                "avg_vis": 26168.25
            },
            "snow": {
                "total_snow": 0.0
            },
            "wind": {
                "avg_wind": 14.49,
                "max_gusts": 68.76,
                "avg_gusts": 26
            }
        }
    },
    "Copper Mountain": {
        "today": {
            "temps": {
                "min_temp": 16.6,
                "max_temp": 20.74,
                "avg_temp": 18.1
            },
            "vis": {
                "min_vis": 5400.0,
                "max_vis": 28800.0,
                "avg_vis": 20444.45
            },
            "snow": {
                "total_snow": 0.0
            },
            "wind": {
                "avg_wind": 12.74,
                "max_gusts": 32.76,
                "avg_gusts": 25
            }
        },
        "three_day": {
            "temps": {
                "min_temp": 16.6,
                "max_temp": 32.08,
                "avg_temp": 21.32
            },
            "vis": {
                "min_vis": 5400.0,
                "max_vis": 54100.0,
                "avg_vis": 34729.63
            },
            "snow": {
                "total_snow": 0.0
            },
            "wind": {
                "avg_wind": 9.11,
                "max_gusts": 38.16,
                "avg_gusts": 21
            }
        },
        "seven_day": {
            "temps": {
                "min_temp": 10.3,
                "max_temp": 33.61,
                "avg_temp": 20.3
            },
            "vis": {
                "min_vis": 5400.0,
                "max_vis": 55800.0,
                "avg_vis": 31242.86
            },
            "snow": {
                "total_snow": 0.0
            },
            "wind": {
                "avg_wind": 8.98,
                "max_gusts": 61.92,
                "avg_gusts": 24
            }
        }
    },
    "Eldora": {
        "today": {
            "temps": {
                "min_temp": 20.37,
                "max_temp": 24.06,
                "avg_temp": 23.01
            },
            "vis": {
                "min_vis": 200.0,
                "max_vis": 12200.0,
                "avg_vis": 3344.44
            },
            "snow": {
                "total_snow": 0.0
            },
            "wind": {
                "avg_wind": 5.81,
                "max_gusts": 19.08,
                "avg_gusts": 15
            }
        },
        "three_day": {
            "temps": {
                "min_temp": 20.37,
                "max_temp": 42.24,
                "avg_temp": 29.67
            },
            "vis": {
                "min_vis": 200.0,
                "max_vis": 77500.0,
                "avg_vis": 39044.45
            },
            "snow": {
                "total_snow": 0.0
            },
            "wind": {
                "avg_wind": 8.63,
                "max_gusts": 37.44,
                "avg_gusts": 16
            }
        },
        "seven_day": {
            "temps": {
                "min_temp": 20.37,
                "max_temp": 44.67,
                "avg_temp": 30.13
            },
            "vis": {
                "min_vis": 0.0,
                "max_vis": 77500.0,
                "avg_vis": 30860.32
            },
            "snow": {
                "total_snow": 0.0
            },
            "wind": {
                "avg_wind": 10.87,
                "max_gusts": 43.92,
                "avg_gusts": 18
            }
        }
    },
    "Steamboat": {
        "today": {
            "temps": {
                "min_temp": 31.9,
                "max_temp": 34.42,
                "avg_temp": 32.95
            },
            "vis": {
                "min_vis": 300.0,
                "max_vis": 17600.0,
                "avg_vis": 5300.0
            },
            "snow": {
                "total_snow": 0.0
            },
            "wind": {
                "avg_wind": 2.35,
                "max_gusts": 8.64,
                "avg_gusts": 6
            }
        },
        "three_day": {
            "temps": {
                "min_temp": 29.29,
                "max_temp": 39.64,
                "avg_temp": 34.27
            },
            "vis": {
                "min_vis": 300.0,
                "max_vis": 55100.0,
                "avg_vis": 23514.81
            },
            "snow": {
                "total_snow": 0.0
            },
            "wind": {
                "avg_wind": 5.08,
                "max_gusts": 11.52,
                "avg_gusts": 7
            }
        },
        "seven_day": {
            "temps": {
                "min_temp": 24.34,
                "max_temp": 48.1,
                "avg_temp": 34.21
            },
            "vis": {
                "min_vis": 300.0,
                "max_vis": 55100.0,
                "avg_vis": 23371.43
            },
            "snow": {
                "total_snow": 0.0
            },
            "wind": {
                "avg_wind": 6.52,
                "max_gusts": 38.52,
                "avg_gusts": 10
            }
        }
    },
    "Winter Park": {
        "today": {
            "temps": {
                "min_temp": 18.97,
                "max_temp": 26.17,
                "avg_temp": 22.04
            },
            "vis": {
                "min_vis": 18600.0,
                "max_vis": 24800.0,
                "avg_vis": 20822.22
            },
            "snow": {
                "total_snow": 0.0
            },
            "wind": {
                "avg_wind": 13.06,
                "max_gusts": 45.0,
                "avg_gusts": 35
            }
        },
        "three_day": {
            "temps": {
                "min_temp": 18.97,
                "max_temp": 36.97,
                "avg_temp": 26.05
            },
            "vis": {
                "min_vis": 18600.0,
                "max_vis": 64600.0,
                "avg_vis": 34840.74
            },
            "snow": {
                "total_snow": 0.0
            },
            "wind": {
                "avg_wind": 9.29,
                "max_gusts": 45.0,
                "avg_gusts": 18
            }
        },
        "seven_day": {
            "temps": {
                "min_temp": 15.46,
                "max_temp": 49.03,
                "avg_temp": 26.02
            },
            "vis": {
                "min_vis": 300.0,
                "max_vis": 64600.0,
                "avg_vis": 27420.63
            },
            "snow": {
                "total_snow": 0.0
            },
            "wind": {
                "avg_wind": 7.49,
                "max_gusts": 54.0,
                "avg_gusts": 15
            }
        }
    }
}